{
  "last_updated": "2026-03-01T03:41:55.407881Z",
  "source": "ForexFactory",
  "feed_url": "https://nfs.faireconomy.media/ff_calendar_thisweek.xml",
  "event_count": 81,
  "events": [
    {
      "title": "Retail Sales q/q",
      "currency": "NZD",
      "date": "02-22-2026",
      "time_et": "9:45pm",
      "time_24h": "21:45",
      "datetime_utc": "2026-02-23T02:45:00Z",
      "datetime_aest": "2026-02-23T12:45:00",
      "impact": "Medium",
      "impact_level": 2,
      "forecast": "0.6%",
      "previous": "1.9%",
      "url": "https://www.forexfactory.com/calendar/510-nz-retail-sales-qq"
    },
    {
      "title": "Core Retail Sales q/q",
      "currency": "NZD",
      "date": "02-22-2026",
      "time_et": "9:45pm",
      "time_24h": "21:45",
      "datetime_utc": "2026-02-23T02:45:00Z",
      "datetime_aest": "2026-02-23T12:45:00",
      "impact": "Low",
      "impact_level": 1,
      "forecast": "0.4%",
      "previous": "1.2%",
      "url": "https://www.forexfactory.com/calendar/511-nz-core-retail-sales-qq"
    },
    {
      "title": "Bank Holiday",
      "currency": "JPY",
      "date": "02-23-2026",
      "time_et": "12:00am",
      "time_24h": "00:00",
      "datetime_utc": "2026-02-23T05:00:00Z",
      "datetime_aest": "2026-02-23T15:00:00",
      "impact": "Holiday",
      "impact_level": 0,
      "forecast": null,
      "previous": null,
      "url": "https://www.forexfactory.com/calendar/393-jn-bank-holiday"
    },
    {
      "title": "Credit Card Spending y/y",
      "currency": "NZD",
      "date": "02-23-2026",
      "time_et": "2:00am",
      "time_24h": "02:00",
      "datetime_utc": "2026-02-23T07:00:00Z",
      "datetime_aest": "2026-02-23T17:00:00",
      "impact": "Low",
      "impact_level": 1,
      "forecast": null,
      "previous": "-0.3%",
      "url": "https://www.forexfactory.com/calendar/184-nz-credit-card-spending-yy"
    },
    {
      "title": "PPI m/m",
      "currency": "CHF",
      "date": "02-23-2026",
      "time_et": "7:30am",
      "time_24h": "07:30",
      "datetime_utc": "2026-02-23T12:30:00Z",
      "datetime_aest": "2026-02-23T22:30:00",
      "impact": "Low",
      "impact_level": 1,
      "forecast": "0.1%",
      "previous": "-0.2%",
      "url": "https://www.forexfactory.com/calendar/96-sz-ppi-mm"
    },
    {
      "title": "German ifo Business Climate",
      "currency": "EUR",
      "date": "02-23-2026",
      "time_et": "9:00am",
      "time_24h": "09:00",
      "datetime_utc": "2026-02-23T14:00:00Z",
      "datetime_aest": "2026-02-24T00:00:00",
      "impact": "Low",
      "impact_level": 1,
      "forecast": "88.4",
      "previous": "87.6",
      "url": "https://www.forexfactory.com/calendar/316-ge-ifo-business-climate"
    },
    {
      "title": "MPC Member Taylor Speaks",
      "currency": "GBP",
      "date": "02-23-2026",
      "time_et": "11:00am",
      "time_24h": "11:00",
      "datetime_utc": "2026-02-23T16:00:00Z",
      "datetime_aest": "2026-02-24T02:00:00",
      "impact": "Low",
      "impact_level": 1,
      "forecast": null,
      "previous": null,
      "url": "https://www.forexfactory.com/calendar/916-uk-mpc-member-taylor-speaks"
    },
    {
      "title": "FOMC Member Waller Speaks",
      "currency": "USD",
      "date": "02-23-2026",
      "time_et": "1:00pm",
      "time_24h": "13:00",
      "datetime_utc": "2026-02-23T18:00:00Z",
      "datetime_aest": "2026-02-24T04:00:00",
      "impact": "Medium",
      "impact_level": 2,
      "forecast": null,
      "previous": null,
      "url": "https://www.forexfactory.com/calendar/839-us-fomc-member-waller-speaks"
    },
    {
      "title": "Belgian NBB Business Climate",
      "currency": "EUR",
      "date": "02-23-2026",
      "time_et": "1:26pm",
      "time_24h": "13:26",
      "datetime_utc": "2026-02-23T18:26:00Z",
      "datetime_aest": "2026-02-24T04:26:00",
      "impact": "Low",
      "impact_level": 1,
      "forecast": "-7.5",
      "previous": "-8.8",
      "url": "https://www.forexfactory.com/calendar/317-be-nbb-business-climate"
    },
    {
      "title": "Factory Orders m/m",
      "currency": "USD",
      "date": "02-23-2026",
      "time_et": "3:00pm",
      "time_24h": "15:00",
      "datetime_utc": "2026-02-23T20:00:00Z",
      "datetime_aest": "2026-02-24T06:00:00",
      "impact": "Low",
      "impact_level": 1,
      "forecast": "-0.4%",
      "previous": "2.7%",
      "url": "https://www.forexfactory.com/calendar/351-us-factory-orders-mm"
    },
    {
      "title": "ECB President Lagarde Speaks",
      "currency": "EUR",
      "date": "02-23-2026",
      "time_et": "5:30pm",
      "time_24h": "17:30",
      "datetime_utc": "2026-02-23T22:30:00Z",
      "datetime_aest": "2026-02-24T08:30:00",
      "impact": "Medium",
      "impact_level": 2,
      "forecast": null,
      "previous": null,
      "url": "https://www.forexfactory.com/calendar/832-ez-ecb-president-lagarde-speaks"
    },
    {
      "title": "CBI Realized Sales",
      "currency": "GBP",
      "date": "02-24-2026",
      "time_et": "11:00am",
      "time_24h": "11:00",
      "datetime_utc": "2026-02-24T16:00:00Z",
      "datetime_aest": "2026-02-25T02:00:00",
      "impact": "Low",
      "impact_level": 1,
      "forecast": "-27",
      "previous": "-17",
      "url": "https://www.forexfactory.com/calendar/329-uk-cbi-realized-sales"
    },
    {
      "title": "FOMC Member Goolsbee Speaks",
      "currency": "USD",
      "date": "02-24-2026",
      "time_et": "1:00pm",
      "time_24h": "13:00",
      "datetime_utc": "2026-02-24T18:00:00Z",
      "datetime_aest": "2026-02-25T04:00:00",
      "impact": "Low",
      "impact_level": 1,
      "forecast": null,
      "previous": null,
      "url": "https://www.forexfactory.com/calendar/889-us-fomc-member-goolsbee-speaks"
    },
    {
      "title": "ADP Weekly Employment Change",
      "currency": "USD",
      "date": "02-24-2026",
      "time_et": "1:15pm",
      "time_24h": "13:15",
      "datetime_utc": "2026-02-24T18:15:00Z",
      "datetime_aest": "2026-02-25T04:15:00",
      "impact": "Low",
      "impact_level": 1,
      "forecast": null,
      "previous": "10.3K",
      "url": "https://www.forexfactory.com/calendar/929-us-adp-weekly-employment-change"
    },
    {
      "title": "FOMC Member Bostic Speaks",
      "currency": "USD",
      "date": "02-24-2026",
      "time_et": "2:00pm",
      "time_24h": "14:00",
      "datetime_utc": "2026-02-24T19:00:00Z",
      "datetime_aest": "2026-02-25T05:00:00",
      "impact": "Low",
      "impact_level": 1,
      "forecast": null,
      "previous": null,
      "url": "https://www.forexfactory.com/calendar/725-us-fomc-member-bostic-speaks"
    },
    {
      "title": "FOMC Member Collins Speaks",
      "currency": "USD",
      "date": "02-24-2026",
      "time_et": "2:00pm",
      "time_24h": "14:00",
      "datetime_utc": "2026-02-24T19:00:00Z",
      "datetime_aest": "2026-02-25T05:00:00",
      "impact": "Low",
      "impact_level": 1,
      "forecast": null,
      "previous": null,
      "url": "https://www.forexfactory.com/calendar/882-us-fomc-member-collins-speaks"
    },
    {
      "title": "HPI m/m",
      "currency": "USD",
      "date": "02-24-2026",
      "time_et": "2:00pm",
      "time_24h": "14:00",
      "datetime_utc": "2026-02-24T19:00:00Z",
      "datetime_aest": "2026-02-25T05:00:00",
      "impact": "Low",
      "impact_level": 1,
      "forecast": "0.3%",
      "previous": "0.6%",
      "url": "https://www.forexfactory.com/calendar/239-us-hpi-mm"
    },
    {
      "title": "S&P/CS Composite-20 HPI y/y",
      "currency": "USD",
      "date": "02-24-2026",
      "time_et": "2:00pm",
      "time_24h": "14:00",
      "datetime_utc": "2026-02-24T19:00:00Z",
      "datetime_aest": "2026-02-25T05:00:00",
      "impact": "Low",
      "impact_level": 1,
      "forecast": "1.3%",
      "previous": "1.4%",
      "url": "https://www.forexfactory.com/calendar/240-us-spcs-composite-20-hpi-yy"
    },
    {
      "title": "Monetary Policy Report Hearings",
      "currency": "GBP",
      "date": "02-24-2026",
      "time_et": "2:15pm",
      "time_24h": "14:15",
      "datetime_utc": "2026-02-24T19:15:00Z",
      "datetime_aest": "2026-02-25T05:15:00",
      "impact": "Medium",
      "impact_level": 2,
      "forecast": null,
      "previous": null,
      "url": "https://www.forexfactory.com/calendar/439-uk-monetary-policy-report-hearings"
    },
    {
      "title": "FOMC Member Waller Speaks",
      "currency": "USD",
      "date": "02-24-2026",
      "time_et": "2:15pm",
      "time_24h": "14:15",
      "datetime_utc": "2026-02-24T19:15:00Z",
      "datetime_aest": "2026-02-25T05:15:00",
      "impact": "Low",
      "impact_level": 1,
      "forecast": null,
      "previous": null,
      "url": "https://www.forexfactory.com/calendar/839-us-fomc-member-waller-speaks"
    },
    {
      "title": "FOMC Member Cook Speaks",
      "currency": "USD",
      "date": "02-24-2026",
      "time_et": "2:30pm",
      "time_24h": "14:30",
      "datetime_utc": "2026-02-24T19:30:00Z",
      "datetime_aest": "2026-02-25T05:30:00",
      "impact": "Low",
      "impact_level": 1,
      "forecast": null,
      "previous": null,
      "url": "https://www.forexfactory.com/calendar/886-us-fomc-member-cook-speaks"
    },
    {
      "title": "CB Consumer Confidence",
      "currency": "USD",
      "date": "02-24-2026",
      "time_et": "3:00pm",
      "time_24h": "15:00",
      "datetime_utc": "2026-02-24T20:00:00Z",
      "datetime_aest": "2026-02-25T06:00:00",
      "impact": "Medium",
      "impact_level": 2,
      "forecast": "87.4",
      "previous": "84.5",
      "url": "https://www.forexfactory.com/calendar/208-us-cb-consumer-confidence"
    },
    {
      "title": "Richmond Manufacturing Index",
      "currency": "USD",
      "date": "02-24-2026",
      "time_et": "3:00pm",
      "time_24h": "15:00",
      "datetime_utc": "2026-02-24T20:00:00Z",
      "datetime_aest": "2026-02-25T06:00:00",
      "impact": "Medium",
      "impact_level": 2,
      "forecast": "-8",
      "previous": "-6",
      "url": "https://www.forexfactory.com/calendar/186-us-richmond-manufacturing-index"
    },
    {
      "title": "Final Wholesale Inventories m/m",
      "currency": "USD",
      "date": "02-24-2026",
      "time_et": "3:00pm",
      "time_24h": "15:00",
      "datetime_utc": "2026-02-24T20:00:00Z",
      "datetime_aest": "2026-02-25T06:00:00",
      "impact": "Low",
      "impact_level": 1,
      "forecast": "0.2%",
      "previous": "0.2%",
      "url": "https://www.forexfactory.com/calendar/154-us-final-wholesale-inventories-mm"
    },
    {
      "title": "SNB Chairman Schlegel Speaks",
      "currency": "CHF",
      "date": "02-24-2026",
      "time_et": "5:30pm",
      "time_24h": "17:30",
      "datetime_utc": "2026-02-24T22:30:00Z",
      "datetime_aest": "2026-02-25T08:30:00",
      "impact": "Medium",
      "impact_level": 2,
      "forecast": null,
      "previous": null,
      "url": "https://www.forexfactory.com/calendar/915-sz-snb-chairman-schlegel-speaks"
    },
    {
      "title": "FOMC Member Barkin Speaks",
      "currency": "USD",
      "date": "02-24-2026",
      "time_et": "8:20pm",
      "time_24h": "20:20",
      "datetime_utc": "2026-02-25T01:20:00Z",
      "datetime_aest": "2026-02-25T11:20:00",
      "impact": "Low",
      "impact_level": 1,
      "forecast": null,
      "previous": null,
      "url": "https://www.forexfactory.com/calendar/728-us-fomc-member-barkin-speaks"
    },
    {
      "title": "FOMC Member Collins Speaks",
      "currency": "USD",
      "date": "02-24-2026",
      "time_et": "8:20pm",
      "time_24h": "20:20",
      "datetime_utc": "2026-02-25T01:20:00Z",
      "datetime_aest": "2026-02-25T11:20:00",
      "impact": "Low",
      "impact_level": 1,
      "forecast": null,
      "previous": null,
      "url": "https://www.forexfactory.com/calendar/882-us-fomc-member-collins-speaks"
    },
    {
      "title": "API Weekly Statistical Bulletin",
      "currency": "USD",
      "date": "02-24-2026",
      "time_et": "9:30pm",
      "time_24h": "21:30",
      "datetime_utc": "2026-02-25T02:30:00Z",
      "datetime_aest": "2026-02-25T12:30:00",
      "impact": "Low",
      "impact_level": 1,
      "forecast": null,
      "previous": null,
      "url": "https://www.forexfactory.com/calendar/754-us-api-weekly-statistical-bulletin"
    },
    {
      "title": "SPPI y/y",
      "currency": "JPY",
      "date": "02-24-2026",
      "time_et": "11:50pm",
      "time_24h": "23:50",
      "datetime_utc": "2026-02-25T04:50:00Z",
      "datetime_aest": "2026-02-25T14:50:00",
      "impact": "Low",
      "impact_level": 1,
      "forecast": "2.6%",
      "previous": "2.6%",
      "url": "https://www.forexfactory.com/calendar/176-jn-sppi-yy"
    },
    {
      "title": "CPI m/m",
      "currency": "AUD",
      "date": "02-25-2026",
      "time_et": "12:30am",
      "time_24h": "00:30",
      "datetime_utc": "2026-02-25T05:30:00Z",
      "datetime_aest": "2026-02-25T15:30:00",
      "impact": "High",
      "impact_level": 3,
      "forecast": "0.2%",
      "previous": "1.0%",
      "url": "https://www.forexfactory.com/calendar/98-au-cpi-mm"
    },
    {
      "title": "CPI y/y",
      "currency": "AUD",
      "date": "02-25-2026",
      "time_et": "12:30am",
      "time_24h": "00:30",
      "datetime_utc": "2026-02-25T05:30:00Z",
      "datetime_aest": "2026-02-25T15:30:00",
      "impact": "High",
      "impact_level": 3,
      "forecast": "3.7%",
      "previous": "3.8%",
      "url": "https://www.forexfactory.com/calendar/888-au-cpi-yy"
    },
    {
      "title": "Trimmed Mean CPI m/m",
      "currency": "AUD",
      "date": "02-25-2026",
      "time_et": "12:30am",
      "time_24h": "00:30",
      "datetime_utc": "2026-02-25T05:30:00Z",
      "datetime_aest": "2026-02-25T15:30:00",
      "impact": "High",
      "impact_level": 3,
      "forecast": "0.4%",
      "previous": "0.2%",
      "url": "https://www.forexfactory.com/calendar/99-au-trimmed-mean-cpi-mm"
    },
    {
      "title": "Construction Work Done q/q",
      "currency": "AUD",
      "date": "02-25-2026",
      "time_et": "12:30am",
      "time_24h": "00:30",
      "datetime_utc": "2026-02-25T05:30:00Z",
      "datetime_aest": "2026-02-25T15:30:00",
      "impact": "Low",
      "impact_level": 1,
      "forecast": "1.2%",
      "previous": "-0.7%",
      "url": "https://www.forexfactory.com/calendar/213-au-construction-work-done-qq"
    },
    {
      "title": "President Trump Speaks",
      "currency": "USD",
      "date": "02-25-2026",
      "time_et": "2:00am",
      "time_24h": "02:00",
      "datetime_utc": "2026-02-25T07:00:00Z",
      "datetime_aest": "2026-02-25T17:00:00",
      "impact": "High",
      "impact_level": 3,
      "forecast": null,
      "previous": null,
      "url": "https://www.forexfactory.com/calendar/645-us-president-trump-speaks"
    },
    {
      "title": "BOJ Core CPI y/y",
      "currency": "JPY",
      "date": "02-25-2026",
      "time_et": "5:00am",
      "time_24h": "05:00",
      "datetime_utc": "2026-02-25T10:00:00Z",
      "datetime_aest": "2026-02-25T20:00:00",
      "impact": "Low",
      "impact_level": 1,
      "forecast": "1.8%",
      "previous": "1.9%",
      "url": "https://www.forexfactory.com/calendar/631-jn-boj-core-cpi-yy"
    },
    {
      "title": "German Final GDP q/q",
      "currency": "EUR",
      "date": "02-25-2026",
      "time_et": "7:00am",
      "time_24h": "07:00",
      "datetime_utc": "2026-02-25T12:00:00Z",
      "datetime_aest": "2026-02-25T22:00:00",
      "impact": "Low",
      "impact_level": 1,
      "forecast": "0.3%",
      "previous": "0.3%",
      "url": "https://www.forexfactory.com/calendar/77-ge-final-gdp-qq"
    },
    {
      "title": "German GfK Consumer Climate",
      "currency": "EUR",
      "date": "02-25-2026",
      "time_et": "7:00am",
      "time_24h": "07:00",
      "datetime_utc": "2026-02-25T12:00:00Z",
      "datetime_aest": "2026-02-25T22:00:00",
      "impact": "Low",
      "impact_level": 1,
      "forecast": "-23.0",
      "previous": "-24.1",
      "url": "https://www.forexfactory.com/calendar/335-ge-gfk-consumer-climate"
    },
    {
      "title": "RBA Gov Bullock Speaks",
      "currency": "AUD",
      "date": "02-25-2026",
      "time_et": "8:40am",
      "time_24h": "08:40",
      "datetime_utc": "2026-02-25T13:40:00Z",
      "datetime_aest": "2026-02-25T23:40:00",
      "impact": "Medium",
      "impact_level": 2,
      "forecast": null,
      "previous": null,
      "url": "https://www.forexfactory.com/calendar/671-au-rba-gov-bullock-speaks"
    },
    {
      "title": "UBS Economic Expectations",
      "currency": "CHF",
      "date": "02-25-2026",
      "time_et": "9:00am",
      "time_24h": "09:00",
      "datetime_utc": "2026-02-25T14:00:00Z",
      "datetime_aest": "2026-02-26T00:00:00",
      "impact": "Low",
      "impact_level": 1,
      "forecast": null,
      "previous": "-4.7",
      "url": "https://www.forexfactory.com/calendar/315-sz-ubs-economic-expectations"
    },
    {
      "title": "Final Core CPI y/y",
      "currency": "EUR",
      "date": "02-25-2026",
      "time_et": "10:00am",
      "time_24h": "10:00",
      "datetime_utc": "2026-02-25T15:00:00Z",
      "datetime_aest": "2026-02-26T01:00:00",
      "impact": "Low",
      "impact_level": 1,
      "forecast": "2.2%",
      "previous": "2.2%",
      "url": "https://www.forexfactory.com/calendar/167-ez-final-core-cpi-yy"
    },
    {
      "title": "Final CPI y/y",
      "currency": "EUR",
      "date": "02-25-2026",
      "time_et": "10:00am",
      "time_24h": "10:00",
      "datetime_utc": "2026-02-25T15:00:00Z",
      "datetime_aest": "2026-02-26T01:00:00",
      "impact": "Low",
      "impact_level": 1,
      "forecast": "1.7%",
      "previous": "1.7%",
      "url": "https://www.forexfactory.com/calendar/166-ez-final-cpi-yy"
    },
    {
      "title": "Corporate Profits q/q",
      "currency": "CAD",
      "date": "02-25-2026",
      "time_et": "1:30pm",
      "time_24h": "13:30",
      "datetime_utc": "2026-02-25T18:30:00Z",
      "datetime_aest": "2026-02-26T04:30:00",
      "impact": "Low",
      "impact_level": 1,
      "forecast": null,
      "previous": "7.6%",
      "url": "https://www.forexfactory.com/calendar/379-ca-corporate-profits-qq"
    },
    {
      "title": "FOMC Member Barkin Speaks",
      "currency": "USD",
      "date": "02-25-2026",
      "time_et": "2:30pm",
      "time_24h": "14:30",
      "datetime_utc": "2026-02-25T19:30:00Z",
      "datetime_aest": "2026-02-26T05:30:00",
      "impact": "Low",
      "impact_level": 1,
      "forecast": null,
      "previous": null,
      "url": "https://www.forexfactory.com/calendar/728-us-fomc-member-barkin-speaks"
    },
    {
      "title": "Crude Oil Inventories",
      "currency": "USD",
      "date": "02-25-2026",
      "time_et": "3:30pm",
      "time_24h": "15:30",
      "datetime_utc": "2026-02-25T20:30:00Z",
      "datetime_aest": "2026-02-26T06:30:00",
      "impact": "Low",
      "impact_level": 1,
      "forecast": "1.8M",
      "previous": "-9.0M",
      "url": "https://www.forexfactory.com/calendar/10-us-crude-oil-inventories"
    },
    {
      "title": "FOMC Member Schmid Speaks",
      "currency": "USD",
      "date": "02-25-2026",
      "time_et": "4:00pm",
      "time_24h": "16:00",
      "datetime_utc": "2026-02-25T21:00:00Z",
      "datetime_aest": "2026-02-26T07:00:00",
      "impact": "Low",
      "impact_level": 1,
      "forecast": null,
      "previous": null,
      "url": "https://www.forexfactory.com/calendar/912-us-fomc-member-schmid-speaks"
    },
    {
      "title": "FOMC Member Musalem Speaks",
      "currency": "USD",
      "date": "02-25-2026",
      "time_et": "6:20pm",
      "time_24h": "18:20",
      "datetime_utc": "2026-02-25T23:20:00Z",
      "datetime_aest": "2026-02-26T09:20:00",
      "impact": "Low",
      "impact_level": 1,
      "forecast": null,
      "previous": null,
      "url": "https://www.forexfactory.com/calendar/911-us-fomc-member-musalem-speaks"
    },
    {
      "title": "ANZ Business Confidence",
      "currency": "NZD",
      "date": "02-26-2026",
      "time_et": "12:00am",
      "time_24h": "00:00",
      "datetime_utc": "2026-02-26T05:00:00Z",
      "datetime_aest": "2026-02-26T15:00:00",
      "impact": "Low",
      "impact_level": 1,
      "forecast": null,
      "previous": "64.1",
      "url": "https://www.forexfactory.com/calendar/319-nz-anz-business-confidence"
    },
    {
      "title": "Private Capital Expenditure q/q",
      "currency": "AUD",
      "date": "02-26-2026",
      "time_et": "12:30am",
      "time_24h": "00:30",
      "datetime_utc": "2026-02-26T05:30:00Z",
      "datetime_aest": "2026-02-26T15:30:00",
      "impact": "Low",
      "impact_level": 1,
      "forecast": "-0.1%",
      "previous": "6.4%",
      "url": "https://www.forexfactory.com/calendar/381-au-private-capital-expenditure-qq"
    },
    {
      "title": "RBA Bulletin",
      "currency": "AUD",
      "date": "02-26-2026",
      "time_et": "12:30am",
      "time_24h": "00:30",
      "datetime_utc": "2026-02-26T05:30:00Z",
      "datetime_aest": "2026-02-26T15:30:00",
      "impact": "Low",
      "impact_level": 1,
      "forecast": null,
      "previous": null,
      "url": "https://www.forexfactory.com/calendar/333-au-rba-bulletin"
    },
    {
      "title": "ECB President Lagarde Speaks",
      "currency": "EUR",
      "date": "02-26-2026",
      "time_et": "8:30am",
      "time_24h": "08:30",
      "datetime_utc": "2026-02-26T13:30:00Z",
      "datetime_aest": "2026-02-26T23:30:00",
      "impact": "Medium",
      "impact_level": 2,
      "forecast": null,
      "previous": null,
      "url": "https://www.forexfactory.com/calendar/832-ez-ecb-president-lagarde-speaks"
    },
    {
      "title": "M3 Money Supply y/y",
      "currency": "EUR",
      "date": "02-26-2026",
      "time_et": "9:00am",
      "time_24h": "09:00",
      "datetime_utc": "2026-02-26T14:00:00Z",
      "datetime_aest": "2026-02-27T00:00:00",
      "impact": "Low",
      "impact_level": 1,
      "forecast": "2.9%",
      "previous": "2.8%",
      "url": "https://www.forexfactory.com/calendar/375-ez-m3-money-supply-yy"
    },
    {
      "title": "Private Loans y/y",
      "currency": "EUR",
      "date": "02-26-2026",
      "time_et": "9:00am",
      "time_24h": "09:00",
      "datetime_utc": "2026-02-26T14:00:00Z",
      "datetime_aest": "2026-02-27T00:00:00",
      "impact": "Low",
      "impact_level": 1,
      "forecast": "3.1%",
      "previous": "3.0%",
      "url": "https://www.forexfactory.com/calendar/365-ez-private-loans-yy"
    },
    {
      "title": "MPC Member Lombardelli Speaks",
      "currency": "GBP",
      "date": "02-26-2026",
      "time_et": "9:00am",
      "time_24h": "09:00",
      "datetime_utc": "2026-02-26T14:00:00Z",
      "datetime_aest": "2026-02-27T00:00:00",
      "impact": "Low",
      "impact_level": 1,
      "forecast": null,
      "previous": null,
      "url": "https://www.forexfactory.com/calendar/908-uk-mpc-member-lombardelli-speaks"
    },
    {
      "title": "Italian 10-y Bond Auction",
      "currency": "EUR",
      "date": "02-26-2026",
      "time_et": "10:06am",
      "time_24h": "10:06",
      "datetime_utc": "2026-02-26T15:06:00Z",
      "datetime_aest": "2026-02-27T01:06:00",
      "impact": "Low",
      "impact_level": 1,
      "forecast": null,
      "previous": "3.44|1.6",
      "url": "https://www.forexfactory.com/calendar/524-it-10-y-bond-auction"
    },
    {
      "title": "Current Account",
      "currency": "CAD",
      "date": "02-26-2026",
      "time_et": "1:30pm",
      "time_24h": "13:30",
      "datetime_utc": "2026-02-26T18:30:00Z",
      "datetime_aest": "2026-02-27T04:30:00",
      "impact": "Low",
      "impact_level": 1,
      "forecast": "-8.2B",
      "previous": "-9.7B",
      "url": "https://www.forexfactory.com/calendar/196-ca-current-account"
    },
    {
      "title": "Unemployment Claims",
      "currency": "USD",
      "date": "02-26-2026",
      "time_et": "1:30pm",
      "time_24h": "13:30",
      "datetime_utc": "2026-02-26T18:30:00Z",
      "datetime_aest": "2026-02-27T04:30:00",
      "impact": "High",
      "impact_level": 3,
      "forecast": "217K",
      "previous": "206K",
      "url": "https://www.forexfactory.com/calendar/11-us-unemployment-claims"
    },
    {
      "title": "FOMC Member Bowman Speaks",
      "currency": "USD",
      "date": "02-26-2026",
      "time_et": "3:00pm",
      "time_24h": "15:00",
      "datetime_utc": "2026-02-26T20:00:00Z",
      "datetime_aest": "2026-02-27T06:00:00",
      "impact": "Low",
      "impact_level": 1,
      "forecast": null,
      "previous": null,
      "url": "https://www.forexfactory.com/calendar/812-us-fomc-member-bowman-speaks"
    },
    {
      "title": "Natural Gas Storage",
      "currency": "USD",
      "date": "02-26-2026",
      "time_et": "3:30pm",
      "time_24h": "15:30",
      "datetime_utc": "2026-02-26T20:30:00Z",
      "datetime_aest": "2026-02-27T06:30:00",
      "impact": "Low",
      "impact_level": 1,
      "forecast": "-36B",
      "previous": "-144B",
      "url": "https://www.forexfactory.com/calendar/26-us-natural-gas-storage"
    },
    {
      "title": "Tokyo Core CPI y/y",
      "currency": "JPY",
      "date": "02-26-2026",
      "time_et": "11:30pm",
      "time_24h": "23:30",
      "datetime_utc": "2026-02-27T04:30:00Z",
      "datetime_aest": "2026-02-27T14:30:00",
      "impact": "Medium",
      "impact_level": 2,
      "forecast": "1.7%",
      "previous": "2.0%",
      "url": "https://www.forexfactory.com/calendar/175-jn-tokyo-core-cpi-yy"
    },
    {
      "title": "Prelim Industrial Production m/m",
      "currency": "JPY",
      "date": "02-26-2026",
      "time_et": "11:50pm",
      "time_24h": "23:50",
      "datetime_utc": "2026-02-27T04:50:00Z",
      "datetime_aest": "2026-02-27T14:50:00",
      "impact": "Low",
      "impact_level": 1,
      "forecast": "5.5%",
      "previous": "-0.1%",
      "url": "https://www.forexfactory.com/calendar/225-jn-prelim-industrial-production-mm"
    },
    {
      "title": "Retail Sales y/y",
      "currency": "JPY",
      "date": "02-26-2026",
      "time_et": "11:50pm",
      "time_24h": "23:50",
      "datetime_utc": "2026-02-27T04:50:00Z",
      "datetime_aest": "2026-02-27T14:50:00",
      "impact": "Low",
      "impact_level": 1,
      "forecast": "0.1%",
      "previous": "-0.9%",
      "url": "https://www.forexfactory.com/calendar/115-jn-retail-sales-yy"
    },
    {
      "title": "GfK Consumer Confidence",
      "currency": "GBP",
      "date": "02-27-2026",
      "time_et": "12:01am",
      "time_24h": "00:01",
      "datetime_utc": "2026-02-27T05:01:00Z",
      "datetime_aest": "2026-02-27T15:01:00",
      "impact": "Low",
      "impact_level": 1,
      "forecast": "-15",
      "previous": "-16",
      "url": "https://www.forexfactory.com/calendar/188-uk-gfk-consumer-confidence"
    },
    {
      "title": "Private Sector Credit m/m",
      "currency": "AUD",
      "date": "02-27-2026",
      "time_et": "12:30am",
      "time_24h": "00:30",
      "datetime_utc": "2026-02-27T05:30:00Z",
      "datetime_aest": "2026-02-27T15:30:00",
      "impact": "Low",
      "impact_level": 1,
      "forecast": "0.7%",
      "previous": "0.8%",
      "url": "https://www.forexfactory.com/calendar/344-au-private-sector-credit-mm"
    },
    {
      "title": "Housing Starts y/y",
      "currency": "JPY",
      "date": "02-27-2026",
      "time_et": "5:00am",
      "time_24h": "05:00",
      "datetime_utc": "2026-02-27T10:00:00Z",
      "datetime_aest": "2026-02-27T20:00:00",
      "impact": "Low",
      "impact_level": 1,
      "forecast": "-1.9%",
      "previous": "-1.3%",
      "url": "https://www.forexfactory.com/calendar/228-jn-housing-starts-yy"
    },
    {
      "title": "German Import Prices m/m",
      "currency": "EUR",
      "date": "02-27-2026",
      "time_et": "7:00am",
      "time_24h": "07:00",
      "datetime_utc": "2026-02-27T12:00:00Z",
      "datetime_aest": "2026-02-27T22:00:00",
      "impact": "Low",
      "impact_level": 1,
      "forecast": "0.6%",
      "previous": "-0.1%",
      "url": "https://www.forexfactory.com/calendar/257-ge-import-prices-mm"
    },
    {
      "title": "German Prelim CPI m/m",
      "currency": "EUR",
      "date": "02-27-2026",
      "time_et": "7:29am",
      "time_24h": "07:29",
      "datetime_utc": "2026-02-27T12:29:00Z",
      "datetime_aest": "2026-02-27T22:29:00",
      "impact": "Medium",
      "impact_level": 2,
      "forecast": "0.5%",
      "previous": "0.1%",
      "url": "https://www.forexfactory.com/calendar/169-ge-prelim-cpi-mm"
    },
    {
      "title": "French Consumer Spending m/m",
      "currency": "EUR",
      "date": "02-27-2026",
      "time_et": "7:45am",
      "time_24h": "07:45",
      "datetime_utc": "2026-02-27T12:45:00Z",
      "datetime_aest": "2026-02-27T22:45:00",
      "impact": "Low",
      "impact_level": 1,
      "forecast": "0.4%",
      "previous": "-0.6%",
      "url": "https://www.forexfactory.com/calendar/357-fr-consumer-spending-mm"
    },
    {
      "title": "French Prelim CPI m/m",
      "currency": "EUR",
      "date": "02-27-2026",
      "time_et": "7:45am",
      "time_24h": "07:45",
      "datetime_utc": "2026-02-27T12:45:00Z",
      "datetime_aest": "2026-02-27T22:45:00",
      "impact": "Low",
      "impact_level": 1,
      "forecast": "0.5%",
      "previous": "-0.3%",
      "url": "https://www.forexfactory.com/calendar/556-fr-prelim-cpi-mm"
    },
    {
      "title": "French Prelim GDP q/q",
      "currency": "EUR",
      "date": "02-27-2026",
      "time_et": "7:45am",
      "time_24h": "07:45",
      "datetime_utc": "2026-02-27T12:45:00Z",
      "datetime_aest": "2026-02-27T22:45:00",
      "impact": "Low",
      "impact_level": 1,
      "forecast": "0.2%",
      "previous": "0.2%",
      "url": "https://www.forexfactory.com/calendar/39-fr-prelim-gdp-qq"
    },
    {
      "title": "French Final Private Payrolls q/q",
      "currency": "EUR",
      "date": "02-27-2026",
      "time_et": "7:48am",
      "time_24h": "07:48",
      "datetime_utc": "2026-02-27T12:48:00Z",
      "datetime_aest": "2026-02-27T22:48:00",
      "impact": "Low",
      "impact_level": 1,
      "forecast": "-0.1%",
      "previous": "-0.1%",
      "url": "https://www.forexfactory.com/calendar/71-fr-final-private-payrolls-qq"
    },
    {
      "title": "GDP q/q",
      "currency": "CHF",
      "date": "02-27-2026",
      "time_et": "8:00am",
      "time_24h": "08:00",
      "datetime_utc": "2026-02-27T13:00:00Z",
      "datetime_aest": "2026-02-27T23:00:00",
      "impact": "Low",
      "impact_level": 1,
      "forecast": "0.2%",
      "previous": "-0.5%",
      "url": "https://www.forexfactory.com/calendar/32-sz-gdp-qq"
    },
    {
      "title": "KOF Economic Barometer",
      "currency": "CHF",
      "date": "02-27-2026",
      "time_et": "8:00am",
      "time_24h": "08:00",
      "datetime_utc": "2026-02-27T13:00:00Z",
      "datetime_aest": "2026-02-27T23:00:00",
      "impact": "Low",
      "impact_level": 1,
      "forecast": "103.0",
      "previous": "102.5",
      "url": "https://www.forexfactory.com/calendar/301-sz-kof-economic-barometer"
    },
    {
      "title": "Spanish Flash CPI y/y",
      "currency": "EUR",
      "date": "02-27-2026",
      "time_et": "8:00am",
      "time_24h": "08:00",
      "datetime_utc": "2026-02-27T13:00:00Z",
      "datetime_aest": "2026-02-27T23:00:00",
      "impact": "Low",
      "impact_level": 1,
      "forecast": "2.2%",
      "previous": "2.4%",
      "url": "https://www.forexfactory.com/calendar/592-sp-flash-cpi-yy"
    },
    {
      "title": "German Unemployment Change",
      "currency": "EUR",
      "date": "02-27-2026",
      "time_et": "8:55am",
      "time_24h": "08:55",
      "datetime_utc": "2026-02-27T13:55:00Z",
      "datetime_aest": "2026-02-27T23:55:00",
      "impact": "Low",
      "impact_level": 1,
      "forecast": "2K",
      "previous": "0K",
      "url": "https://www.forexfactory.com/calendar/60-ge-unemployment-change"
    },
    {
      "title": "MPC Member Pill Speaks",
      "currency": "GBP",
      "date": "02-27-2026",
      "time_et": "1:00pm",
      "time_24h": "13:00",
      "datetime_utc": "2026-02-27T18:00:00Z",
      "datetime_aest": "2026-02-28T04:00:00",
      "impact": "Low",
      "impact_level": 1,
      "forecast": null,
      "previous": null,
      "url": "https://www.forexfactory.com/calendar/850-uk-mpc-member-pill-speaks"
    },
    {
      "title": "GDP m/m",
      "currency": "CAD",
      "date": "02-27-2026",
      "time_et": "1:30pm",
      "time_24h": "13:30",
      "datetime_utc": "2026-02-27T18:30:00Z",
      "datetime_aest": "2026-02-28T04:30:00",
      "impact": "High",
      "impact_level": 3,
      "forecast": "0.1%",
      "previous": "0.0%",
      "url": "https://www.forexfactory.com/calendar/29-ca-gdp-mm"
    },
    {
      "title": "Core PPI m/m",
      "currency": "USD",
      "date": "02-27-2026",
      "time_et": "1:30pm",
      "time_24h": "13:30",
      "datetime_utc": "2026-02-27T18:30:00Z",
      "datetime_aest": "2026-02-28T04:30:00",
      "impact": "High",
      "impact_level": 3,
      "forecast": "0.3%",
      "previous": "0.7%",
      "url": "https://www.forexfactory.com/calendar/87-us-core-ppi-mm"
    },
    {
      "title": "PPI m/m",
      "currency": "USD",
      "date": "02-27-2026",
      "time_et": "1:30pm",
      "time_24h": "13:30",
      "datetime_utc": "2026-02-27T18:30:00Z",
      "datetime_aest": "2026-02-28T04:30:00",
      "impact": "High",
      "impact_level": 3,
      "forecast": "0.3%",
      "previous": "0.5%",
      "url": "https://www.forexfactory.com/calendar/86-us-ppi-mm"
    },
    {
      "title": "Chicago PMI",
      "currency": "USD",
      "date": "02-27-2026",
      "time_et": "2:45pm",
      "time_24h": "14:45",
      "datetime_utc": "2026-02-27T19:45:00Z",
      "datetime_aest": "2026-02-28T05:45:00",
      "impact": "Low",
      "impact_level": 1,
      "forecast": "52.0",
      "previous": "54.0",
      "url": "https://www.forexfactory.com/calendar/189-us-chicago-pmi"
    },
    {
      "title": "Construction Spending m/m",
      "currency": "USD",
      "date": "02-27-2026",
      "time_et": "2:59pm",
      "time_24h": "14:59",
      "datetime_utc": "2026-02-27T19:59:00Z",
      "datetime_aest": "2026-02-28T05:59:00",
      "impact": "Low",
      "impact_level": 1,
      "forecast": null,
      "previous": "0.5%",
      "url": "https://www.forexfactory.com/calendar/205-us-construction-spending-mm"
    },
    {
      "title": "Construction Spending m/m",
      "currency": "USD",
      "date": "02-27-2026",
      "time_et": "3:00pm",
      "time_24h": "15:00",
      "datetime_utc": "2026-02-27T20:00:00Z",
      "datetime_aest": "2026-02-28T06:00:00",
      "impact": "Low",
      "impact_level": 1,
      "forecast": "0.2%",
      "previous": "-0.2%",
      "url": "https://www.forexfactory.com/calendar/205-us-construction-spending-mm"
    }
  ]
}